Workbook

Sheet Summary
A1: Order Dataset - Descriptive Statistics & Key Findings
A2: Source: Assignment_Week_2_project.xlsx | 1,200 orders, Jan 2023 - Jun 2025 | All figures below are live formulas on the Data sheet
A4: Metric | B4: Total Price | C4: Unit Price | D4: Quantity | E4: Items in Cart
A5: Count | B5: =COUNT(Data!$N$2:$N$1201) -> 1200 | C5: =COUNT(Data!$F$2:$F$1201) -> 1200 | D5: =COUNT(Data!$E$2:$E$1201) -> 1200 | E5: =COUNT(Data!$K$2:$K$1201) -> 1200
A6: Mean | B6: =AVERAGE(Data!$N$2:$N$1201) -> 1053.9683 | C6: =AVERAGE(Data!$F$2:$F$1201) -> 356.41275 | D6: =AVERAGE(Data!$E$2:$E$1201) -> 2.9458333 | E6: =AVERAGE(Data!$K$2:$K$1201) -> 5.485
A7: Median | B7: =MEDIAN(Data!$N$2:$N$1201) -> 823.615 | C7: =MEDIAN(Data!$F$2:$F$1201) -> 364.21 | D7: =MEDIAN(Data!$E$2:$E$1201) -> 3 | E7: =MEDIAN(Data!$K$2:$K$1201) -> 5
A8: Std Dev | B8: =STDEV(Data!$N$2:$N$1201) -> 819.85656 | C8: =STDEV(Data!$F$2:$F$1201) -> 197.17715 | D8: =STDEV(Data!$E$2:$E$1201) -> 1.4075571 | E8: =STDEV(Data!$K$2:$K$1201) -> 2.2819833
A9: Min | B9: =MIN(Data!$N$2:$N$1201) -> 11.39 | C9: =MIN(Data!$F$2:$F$1201) -> 11.39 | D9: =MIN(Data!$E$2:$E$1201) -> 1 | E9: =MIN(Data!$K$2:$K$1201) -> 1
A10: Max | B10: =MAX(Data!$N$2:$N$1201) -> 3456.4 | C10: =MAX(Data!$F$2:$F$1201) -> 699.93 | D10: =MAX(Data!$E$2:$E$1201) -> 5 | E10: =MAX(Data!$K$2:$K$1201) -> 10
A11: Skewness | B11: =SKEW(Data!$N$2:$N$1201) -> 0.89135908 | C11: =SKEW(Data!$F$2:$F$1201) -> -0.026511641 | D11: =SKEW(Data!$E$2:$E$1201) -> 0.027922314 | E11: =SKEW(Data!$K$2:$K$1201) -> 0.00087679985
A12: Note: currency columns (Total/Unit Price) are in $; Quantity and Items in Cart are unit counts.
A13: Outlier test (Total Price, IQR method) | B13: Value
A14: Q1 (25th percentile) | B14: =QUARTILE(Data!$N$2:$N$1201,1) -> 410.52
A15: Q3 (75th percentile) | B15: =QUARTILE(Data!$N$2:$N$1201,3) -> 1578.475
A16: IQR | B16: =B15-B14 -> 1167.955
A17: Upper fence (Q3 + 1.5 x IQR) | B17: =B15+1.5*B16 -> 3330.4075 | C17: =B17 -> 3330.4075
A18: Lower fence (Q1 - 1.5 x IQR) | B18: =B14-1.5*B16 -> -1341.4125
A19: Orders above upper fence | B19: =COUNTIF(Data!$N$2:$N$1201,">"&B17) -> 8
A20: Share of all orders | B20: =B19/B5 -> 0.0066666667
A22: Headline figures | B22: Value
A23: Gross revenue | B23: =SUM(Data!$N$2:$N$1201) -> 1264762
A24: Revenue from Cancelled + Returned | B24: =SUMIFS(Data!$N$2:$N$1201,Data!$I$2:$I$1201,"Cancelled")+SUMIFS(Data!$N$2:$N$1201,Data!$I$2:$I$1201,"Returned") -> 519673.91
A25: Net revenue (excl. Cancelled/Returned) | B25: =B23-B24 -> 745088.05
A26: Net as % of gross | B26: =B25/B23 -> 0.58911327
A27: Cancelled + Returned orders | B27: =COUNTIF(Data!$I$2:$I$1201,"Cancelled")+COUNTIF(Data!$I$2:$I$1201,"Returned") -> 497
A28: % of orders Cancelled/Returned | B28: =B27/B5 -> 0.41416667
A29: Unique customers | B29: =SUMPRODUCT(1/COUNTIF(Data!$C$2:$C$1201,Data!$C$2:$C$1201)) -> 1189
A30: Orders with no coupon | B30: =COUNTIF(Data!$R$2:$R$1201,"None") -> 309
A31: Top-10% orders: share of revenue | B31: =SUMIF(Data!$N$2:$N$1201,">="&PERCENTILE(Data!$N$2:$N$1201,0.9))/B23 -> 0.26264756
A33: Key observations
A34: 1. Revenue is declining ~10% per year on a like-for-like Jan-Jun basis; the drop is driven mainly by lower average order value, with order counts down only modestly (see Trends).
A35: 2. About 41% of orders and value are Cancelled or Returned; net revenue is roughly 59% of gross. This is the largest issue in the data.
A36: 3. Order value is driven by unit price and quantity. Product type, coupon, payment method and referral source show no material difference in average order value (see Segments).
A37: 4. Only 8 orders (0.7%) breach the IQR upper fence; all are Quantity 5 at unit price above $665. They are valid large orders, not errors. No outliers by z-score.
A38: 5. No true seasonality: Jan-Jun looks stronger only because it appears in 3 years vs 2 for Jul-Dec. Orders per year are ~240 in each half.
A39: 6. Data-quality flags: TotalPrice equals Quantity x UnitPrice on every row (coupon discounts not reflected); every order has a tracking number, even Cancelled/Pending; status split is near-uniform, which looks synthetic.

Sheet Trends
A1: Trends Over Time
A2: H1 = Jan 1 - Jun 30 (the only period available in all three years, so the fair like-for-like comparison)
A4: Year (H1) | B4: Orders | C4: Revenue ($) | D4: Avg Order Value ($) | E4: Orders YoY | F4: Revenue YoY | G4: AOV YoY
A5: 2023 | B5: =COUNTIFS(Data!$B$2:$B$1201,">="&DATE(A5,1,1),Data!$B$2:$B$1201,"<="&DATE(A5,6,30)) -> 252 | C5: =SUMIFS(Data!$N$2:$N$1201,Data!$B$2:$B$1201,">="&DATE(A5,1,1),Data!$B$2:$B$1201,"<="&DATE(A5,6,30)) -> 286501.52 | D5: =C5/B5 -> 1136.9108 | E5: n/a | F5: n/a | G5: n/a
A6: 2024 | B6: =COUNTIFS(Data!$B$2:$B$1201,">="&DATE(A6,1,1),Data!$B$2:$B$1201,"<="&DATE(A6,6,30)) -> 237 | C6: =SUMIFS(Data!$N$2:$N$1201,Data!$B$2:$B$1201,">="&DATE(A6,1,1),Data!$B$2:$B$1201,"<="&DATE(A6,6,30)) -> 257059.34 | D6: =C6/B6 -> 1084.6386 | E6: =B6/B5-1 -> -0.05952381 | F6: =C6/C5-1 -> -0.10276448 | G6: =D6/D5-1 -> -0.045977423
A7: 2025 | B7: =COUNTIFS(Data!$B$2:$B$1201,">="&DATE(A7,1,1),Data!$B$2:$B$1201,"<="&DATE(A7,6,30)) -> 231 | C7: =SUMIFS(Data!$N$2:$N$1201,Data!$B$2:$B$1201,">="&DATE(A7,1,1),Data!$B$2:$B$1201,"<="&DATE(A7,6,30)) -> 231882.85 | D7: =C7/B7 -> 1003.8219 | E7: =B7/B6-1 -> -0.025316456 | F7: =C7/C6-1 -> -0.097940382 | G7: =D7/D6-1 -> -0.074510262
A10: Half-year check | B10: Orders | C10: Orders per year
A11: Jan-Jun (3 years of data) | B11: =COUNTIFS(Data!$B$2:$B$1201,">="&DATE(2023,1,1),Data!$B$2:$B$1201,"<="&DATE(2023,6,30))+B6+B7 -> 720 | C11: =B11/3 -> 240
A12: Jul-Dec (2 years of data) | B12: =COUNT(Data!$B$2:$B$1201)-B11 -> 480 | C12: =B12/2 -> 240
A13: Orders per year are equal in both halves, so there is no seasonality; the raw Jan-Jun lead is a coverage artifact.
A15: Month | B15: Orders | C15: Revenue ($) | D15: Avg Order Value ($)
A16: 44927 | B16: =COUNTIFS(Data!$P$2:$P$1201,A16) -> 47 | C16: =SUMIFS(Data!$N$2:$N$1201,Data!$P$2:$P$1201,A16) -> 56685.75 | D16: =IF(B16=0,0,C16/B16) -> 1206.0798
A17: 44958 | B17: =COUNTIFS(Data!$P$2:$P$1201,A17) -> 37 | C17: =SUMIFS(Data!$N$2:$N$1201,Data!$P$2:$P$1201,A17) -> 40117.66 | D17: =IF(B17=0,0,C17/B17) -> 1084.2611
A18: 44986 | B18: =COUNTIFS(Data!$P$2:$P$1201,A18) -> 43 | C18: =SUMIFS(Data!$N$2:$N$1201,Data!$P$2:$P$1201,A18) -> 48609.37 | D18: =IF(B18=0,0,C18/B18) -> 1130.4505
A19: 45017 | B19: =COUNTIFS(Data!$P$2:$P$1201,A19) -> 31 | C19: =SUMIFS(Data!$N$2:$N$1201,Data!$P$2:$P$1201,A19) -> 27751.71 | D19: =IF(B19=0,0,C19/B19) -> 895.21645
A20: 45047 | B20: =COUNTIFS(Data!$P$2:$P$1201,A20) -> 49 | C20: =SUMIFS(Data!$N$2:$N$1201,Data!$P$2:$P$1201,A20) -> 63836.84 | D20: =IF(B20=0,0,C20/B20) -> 1302.7927
A21: 45078 | B21: =COUNTIFS(Data!$P$2:$P$1201,A21) -> 45 | C21: =SUMIFS(Data!$N$2:$N$1201,Data!$P$2:$P$1201,A21) -> 49500.19 | D21: =IF(B21=0,0,C21/B21) -> 1100.0042
A22: 45108 | B22: =COUNTIFS(Data!$P$2:$P$1201,A22) -> 44 | C22: =SUMIFS(Data!$N$2:$N$1201,Data!$P$2:$P$1201,A22) -> 42820.66 | D22: =IF(B22=0,0,C22/B22) -> 973.19682
A23: 45139 | B23: =COUNTIFS(Data!$P$2:$P$1201,A23) -> 51 | C23: =SUMIFS(Data!$N$2:$N$1201,Data!$P$2:$P$1201,A23) -> 54352.14 | D23: =IF(B23=0,0,C23/B23) -> 1065.7282
A24: 45170 | B24: =COUNTIFS(Data!$P$2:$P$1201,A24) -> 29 | C24: =SUMIFS(Data!$N$2:$N$1201,Data!$P$2:$P$1201,A24) -> 29526.67 | D24: =IF(B24=0,0,C24/B24) -> 1018.161
A25: 45200 | B25: =COUNTIFS(Data!$P$2:$P$1201,A25) -> 47 | C25: =SUMIFS(Data!$N$2:$N$1201,Data!$P$2:$P$1201,A25) -> 52607.85 | D25: =IF(B25=0,0,C25/B25) -> 1119.316
A26: 45231 | B26: =COUNTIFS(Data!$P$2:$P$1201,A26) -> 41 | C26: =SUMIFS(Data!$N$2:$N$1201,Data!$P$2:$P$1201,A26) -> 43079.67 | D26: =IF(B26=0,0,C26/B26) -> 1050.7237
A27: 45261 | B27: =COUNTIFS(Data!$P$2:$P$1201,A27) -> 46 | C27: =SUMIFS(Data!$N$2:$N$1201,Data!$P$2:$P$1201,A27) -> 43754.73 | D27: =IF(B27=0,0,C27/B27) -> 951.18978
... A45: 45809 | B45: =COUNTIFS(Data!$P$2:$P$1201,A45) -> 49 | C45: =SUMIFS(Data!$N$2:$N$1201,Data!$P$2:$P$1201,A45) -> 53047.4 | D45: =IF(B45=0,0,C45/B45) -> 1082.6

Sheet Segments
A1: Segment Breakdown
A2: Counts, revenue and average order value by category (formulas on Data sheet)
A4: Product | B4: Orders | C4: Revenue ($) | D4: Avg Order Value ($) | E4: % of Revenue
A5: Chair | B5: =COUNTIF(Data!$D$2:$D$1201,A5) -> 178 | C5: =SUMIFS(Data!$N$2:$N$1201,Data!$D$2:$D$1201,A5) -> 195620.11 | D5: =C5/B5 -> 1098.9894 | E5: =C5/SUM(Data!$N$2:$N$1201) -> 0.15466951
A6: Printer | B6: =COUNTIF(Data!$D$2:$D$1201,A6) -> 181 | C6: =SUMIFS(Data!$N$2:$N$1201,Data!$D$2:$D$1201,A6) -> 195612.61 | D6: =C6/B6 -> 1080.7327 | E6: =C6/SUM(Data!$N$2:$N$1201) -> 0.15466358
A7: Laptop | B7: =COUNTIF(Data!$D$2:$D$1201,A7) -> 173 | C7: =SUMIFS(Data!$N$2:$N$1201,Data!$D$2:$D$1201,A7) -> 192126.56 | D7: =C7/B7 -> 1110.5582 | E7: =C7/SUM(Data!$N$2:$N$1201) -> 0.15190729
A8: Tablet | B8: =COUNTIF(Data!$D$2:$D$1201,A8) -> 179 | C8: =SUMIFS(Data!$N$2:$N$1201,Data!$D$2:$D$1201,A8) -> 186568.95 | D8: =C8/B8 -> 1042.2846 | E8: =C8/SUM(Data!$N$2:$N$1201) -> 0.14751309
A9: Monitor | B9: =COUNTIF(Data!$D$2:$D$1201,A9) -> 163 | C9: =SUMIFS(Data!$N$2:$N$1201,Data!$D$2:$D$1201,A9) -> 175651.41 | D9: =C9/B9 -> 1077.616 | E9: =C9/SUM(Data!$N$2:$N$1201) -> 0.138881
A10: Desk | B10: =COUNTIF(Data!$D$2:$D$1201,A10) -> 170 | C10: =SUMIFS(Data!$N$2:$N$1201,Data!$D$2:$D$1201,A10) -> 167459.93 | D10: =C10/B10 -> 985.05841 | E10: =C10/SUM(Data!$N$2:$N$1201) -> 0.13240431
A11: Phone | B11: =COUNTIF(Data!$D$2:$D$1201,A11) -> 156 | C11: =SUMIFS(Data!$N$2:$N$1201,Data!$D$2:$D$1201,A11) -> 151722.39 | D11: =C11/B11 -> 972.57942 | E11: =C11/SUM(Data!$N$2:$N$1201) -> 0.11996122
A13: Order Status | B13: Orders | C13: Revenue ($) | D13: Avg Order Value ($) | E13: % of Revenue
A14: Delivered | B14: =COUNTIF(Data!$I$2:$I$1201,A14) -> 231 | C14: =SUMIFS(Data!$N$2:$N$1201,Data!$I$2:$I$1201,A14) -> 242600.32 | D14: =C14/B14 -> 1050.2178 | E14: =C14/SUM(Data!$N$2:$N$1201) -> 0.191815
A15: Shipped | B15: =COUNTIF(Data!$I$2:$I$1201,A15) -> 235 | C15: =SUMIFS(Data!$N$2:$N$1201,Data!$I$2:$I$1201,A15) -> 246159.58 | D15: =C15/B15 -> 1047.4876 | E15: =C15/SUM(Data!$N$2:$N$1201) -> 0.19462918
A16: Pending | B16: =COUNTIF(Data!$I$2:$I$1201,A16) -> 237 | C16: =SUMIFS(Data!$N$2:$N$1201,Data!$I$2:$I$1201,A16) -> 256328.15 | D16: =C16/B16 -> 1081.5534 | E16: =C16/SUM(Data!$N$2:$N$1201) -> 0.20266909
A17: Returned | B17: =COUNTIF(Data!$I$2:$I$1201,A17) -> 247 | C17: =SUMIFS(Data!$N$2:$N$1201,Data!$I$2:$I$1201,A17) -> 243277.7 | D17: =C17/B17 -> 984.92996 | E17: =C17/SUM(Data!$N$2:$N$1201) -> 0.19235058
A18: Cancelled | B18: =COUNTIF(Data!$I$2:$I$1201,A18) -> 250 | C18: =SUMIFS(Data!$N$2:$N$1201,Data!$I$2:$I$1201,A18) -> 276396.21 | D18: =C18/B18 -> 1105.5848 | E18: =C18/SUM(Data!$N$2:$N$1201) -> 0.21853615
A20: Payment Method | B20: Orders | C20: Revenue ($) | D20: Avg Order Value ($) | E20: % of Revenue
A21: Cash | B21: =COUNTIF(Data!$H$2:$H$1201,A21) -> 246 | C21: =SUMIFS(Data!$N$2:$N$1201,Data!$H$2:$H$1201,A21) -> 259786.29 | D21: =C21/B21 -> 1056.0418 | E21: =C21/SUM(Data!$N$2:$N$1201) -> 0.20540331
A22: Credit Card | B22: =COUNTIF(Data!$H$2:$H$1201,A22) -> 234 | C22: =SUMIFS(Data!$N$2:$N$1201,Data!$H$2:$H$1201,A22) -> 263847.63 | D22: =C22/B22 -> 1127.554 | E22: =C22/SUM(Data!$N$2:$N$1201) -> 0.20861446
A23: Debit Card | B23: =COUNTIF(Data!$H$2:$H$1201,A23) -> 232 | C23: =SUMIFS(Data!$N$2:$N$1201,Data!$H$2:$H$1201,A23) -> 232361.18 | D23: =C23/B23 -> 1001.5568 | E23: =C23/SUM(Data!$N$2:$N$1201) -> 0.1837193
A24: Gift Card | B24: =COUNTIF(Data!$H$2:$H$1201,A24) -> 230 | C24: =SUMIFS(Data!$N$2:$N$1201,Data!$H$2:$H$1201,A24) -> 246323.92 | D24: =C24/B24 -> 1070.9736 | E24: =C24/SUM(Data!$N$2:$N$1201) -> 0.19475911
A25: Online | B25: =COUNTIF(Data!$H$2:$H$1201,A25) -> 258 | C25: =SUMIFS(Data!$N$2:$N$1201,Data!$H$2:$H$1201,A25) -> 262442.94 | D25: =C25/B25 -> 1017.2207 | E25: =C25/SUM(Data!$N$2:$N$1201) -> 0.20750382
A27: Coupon Code | B27: Orders | C27: Revenue ($) | D27: Avg Order Value ($) | E27: % of Revenue
A28: None | B28: =COUNTIF(Data!$R$2:$R$1201,A28) -> 309 | C28: =SUMIFS(Data!$N$2:$N$1201,Data!$R$2:$R$1201,A28) -> 322401.41 | D28: =C28/B28 -> 1043.3703 | E28: =C28/SUM(Data!$N$2:$N$1201) -> 0.25491074
A29: FREESHIP | B29: =COUNTIF(Data!$R$2:$R$1201,A29) -> 313 | C29: =SUMIFS(Data!$N$2:$N$1201,Data!$R$2:$R$1201,A29) -> 335036.99 | D29: =C29/B29 -> 1070.4057 | E29: =C29/SUM(Data!$N$2:$N$1201) -> 0.26490122
A30: SAVE10 | B30: =COUNTIF(Data!$R$2:$R$1201,A30) -> 286 | C30: =SUMIFS(Data!$N$2:$N$1201,Data!$R$2:$R$1201,A30) -> 304840.02 | D30: =C30/B30 -> 1065.8742 | E30: =C30/SUM(Data!$N$2:$N$1201) -> 0.24102561
A31: WINTER15 | B31: =COUNTIF(Data!$R$2:$R$1201,A31) -> 292 | C31: =SUMIFS(Data!$N$2:$N$1201,Data!$R$2:$R$1201,A31) -> 302483.54 | D31: =C31/B31 -> 1035.9025 | E31: =C31/SUM(Data!$N$2:$N$1201) -> 0.23916243
A33: Referral Source | B33: Orders | C33: Revenue ($) | D33: Avg Order Value ($) | E33: % of Revenue
A34: Email | B34: =COUNTIF(Data!$M$2:$M$1201,A34) -> 250 | C34: =SUMIFS(Data!$N$2:$N$1201,Data!$M$2:$M$1201,A34) -> 261808.55 | D34: =C34/B34 -> 1047.2342 | E34: =C34/SUM(Data!$N$2:$N$1201) -> 0.20700223
A35: Facebook | B35: =COUNTIF(Data!$M$2:$M$1201,A35) -> 228 | C35: =SUMIFS(Data!$N$2:$N$1201,Data!$M$2:$M$1201,A35) -> 250410.9 | D35: =C35/B35 -> 1098.2934 | E35: =C35/SUM(Data!$N$2:$N$1201) -> 0.19799054
A36: Google | B36: =COUNTIF(Data!$M$2:$M$1201,A36) -> 241 | C36: =SUMIFS(Data!$N$2:$N$1201,Data!$M$2:$M$1201,A36) -> 250441.48 | D36: =C36/B36 -> 1039.1763 | E36: =C36/SUM(Data!$N$2:$N$1201) -> 0.19801472
A37: Instagram | B37: =COUNTIF(Data!$M$2:$M$1201,A37) -> 259 | C37: =SUMIFS(Data!$N$2:$N$1201,Data!$M$2:$M$1201,A37) -> 275285.45 | D37: =C37/B37 -> 1062.8782 | E37: =C37/SUM(Data!$N$2:$N$1201) -> 0.21765791
A38: Referral | B38: =COUNTIF(Data!$M$2:$M$1201,A38) -> 222 | C38: =SUMIFS(Data!$N$2:$N$1201,Data!$M$2:$M$1201,A38) -> 226815.58 | D38: =C38/B38 -> 1021.6918 | E38: =C38/SUM(Data!$N$2:$N$1201) -> 0.1793346

Sheet Outliers
A1: Total Price Outliers (IQR method)
A2: Static extract of orders above the upper fence on Summary!B17; the count on Summary!B19 is live and will differ if data changes
A4: OrderID | B4: Date | C4: Product | D4: Quantity | E4: Unit Price | F4: Total Price | G4: Order Status
A5: ORD200789 | B5: 45155 | C5: Tablet | D5: 5 | E5: 691.28 | F5: 3456.4 | G5: Delivered
A6: ORD201122 | B6: 45084 | C6: Monitor | D6: 5 | E6: 678.19 | F6: 3390.95 | G6: Returned
A7: ORD200632 | B7: 45048 | C7: Laptop | D7: 5 | E7: 678.16 | F7: 3390.8 | G7: Delivered
A8: ORD200469 | B8: 45256 | C8: Chair | D8: 5 | E8: 676.98 | F8: 3384.9 | G8: Cancelled
A9: ORD200328 | B9: 44985 | C9: Tablet | D9: 5 | E9: 674.04 | F9: 3370.2 | G9: Cancelled
A10: ORD200107 | B10: 45012 | C10: Printer | D10: 5 | E10: 670.75 | F10: 3353.75 | G10: Shipped
A11: ORD200326 | B11: 45474 | C11: Laptop | D11: 5 | E11: 670.48 | F11: 3352.4 | G11: Returned
A12: ORD201065 | B12: 45229 | C12: Printer | D12: 5 | E12: 666.8 | F12: 3334 | G12: Delivered
A14: All outliers are Quantity 5 at unit prices above $665: legitimate large orders rather than data errors.

Sheet Data
A1: OrderID | B1: Date | C1: CustomerID | D1: Product | E1: Quantity | F1: UnitPrice | G1: ShippingAddress | H1: PaymentMethod | I1: OrderStatus | J1: TrackingNumber | K1: ItemsInCart | L1: CouponCode | M1: ReferralSource | N1: TotalPrice | O1: Year | P1: Month | Q1: OutlierFlag | R1: CouponClean
A2: ORD200000 | B2: 44930 | C2: C72649 | D2: Monitor | E2: 5 | F2: 570.62 | G2: 928 Main St | H2: Debit Card | I2: Shipped | J2: TRK37947903 | K2: 7 | L2: SAVE10 | M2: Instagram | N2: 2853.1 | O2: =YEAR(B2) -> 2023 | P2: =DATE(YEAR(B2),MONTH(B2),1) -> 44927 | Q2: =IF(N2>Summary!$C$17,"Outlier","") | R2: =IF(L2="","None",L2) -> SAVE10
A3: ORD200001 | B3: 45527 | C3: C75739 | D3: Phone | E3: 2 | F3: 151.35 | G3: 823 Main St | H3: Online | I3: Shipped | J3: TRK91186779 | K3: 3 | L3: SAVE10 | M3: Referral | N3: 302.7 | O3: =YEAR(B3) -> 2024 | P3: =DATE(YEAR(B3),MONTH(B3),1) -> 45505 | Q3: =IF(N3>Summary!$C$17,"Outlier","") | R3: =IF(L3="","None",L3) -> SAVE10
A4: ORD200002 | B4: 45349 | C4: C81728 | D4: Tablet | E4: 5 | F4: 550.68 | G4: 512 Main St | H4: Credit Card | I4: Cancelled | J4: TRK42903982 | K4: 8 | L4: FREESHIP | M4: Email | N4: 2753.4 | O4: =YEAR(B4) -> 2024 | P4: =DATE(YEAR(B4),MONTH(B4),1) -> 45323 | Q4: =IF(N4>Summary!$C$17,"Outlier","") | R4: =IF(L4="","None",L4) -> FREESHIP
A5: ORD200003 | B5: 45214 | C5: C33540 | D5: Chair | E5: 1 | F5: 273.19 | G5: 275 Main St | H5: Debit Card | I5: Returned | J5: TRK62788070 | K5: 5 | L5: SAVE10 | M5: Facebook | N5: 273.19 | O5: =YEAR(B5) -> 2023 | P5: =DATE(YEAR(B5),MONTH(B5),1) -> 45200 | Q5: =IF(N5>Summary!$C$17,"Outlier","") | R5: =IF(L5="","None",L5) -> SAVE10
A6: ORD200004 | B6: 45785 | C6: C81840 | D6: Printer | E6: 4 | F6: 626.01 | G6: 668 Main St | H6: Online | I6: Delivered | J6: TRK29241424 | K6: 8 | L6: SAVE10 | M6: Email | N6: 2504.04 | O6: =YEAR(B6) -> 2025 | P6: =DATE(YEAR(B6),MONTH(B6),1) -> 45778 | Q6: =IF(N6>Summary!$C$17,"Outlier","") | R6: =IF(L6="","None",L6) -> SAVE10
A7: ORD200005 | B7: 45222 | C7: C37249 | D7: Phone | E7: 2 | F7: 245.86 | G7: 934 Main St | H7: Credit Card | I7: Shipped | J7: TRK72976927 | K7: 4 | L7: SAVE10 | M7: Instagram | N7: 491.72 | O7: =YEAR(B7) -> 2023 | P7: =DATE(YEAR(B7),MONTH(B7),1) -> 45200 | Q7: =IF(N7>Summary!$C$17,"Outlier","") | R7: =IF(L7="","None",L7) -> SAVE10
A8: ORD200006 | B8: 45825 | C8: C83492 | D8: Laptop | E8: 1 | F8: 664.42 | G8: 986 Main St | H8: Gift Card | I8: Returned | J8: TRK96417362 | K8: 6 | L8: SAVE10 | M8: Facebook | N8: 664.42 | O8: =YEAR(B8) -> 2025 | P8: =DATE(YEAR(B8),MONTH(B8),1) -> 45809 | Q8: =IF(N8>Summary!$C$17,"Outlier","") | R8: =IF(L8="","None",L8) -> SAVE10
A9: ORD200007 | B9: 45058 | C9: C41460 | D9: Monitor | E9: 5 | F9: 149.55 | G9: 706 Main St | H9: Cash | I9: Shipped | J9: TRK78809193 | K9: 9 | L9: FREESHIP | M9: Facebook | N9: 747.75 | O9: =YEAR(B9) -> 2023 | P9: =DATE(YEAR(B9),MONTH(B9),1) -> 45047 | Q9: =IF(N9>Summary!$C$17,"Outlier","") | R9: =IF(L9="","None",L9) -> FREESHIP
A10: ORD200008 | B10: 45749 | C10: C26817 | D10: Phone | E10: 2 | F10: 134.28 | G10: 904 Main St | H10: Gift Card | I10: Cancelled | J10: TRK61042692 | K10: 2 | M10: Email | N10: 268.56 | O10: =YEAR(B10) -> 2025 | P10: =DATE(YEAR(B10),MONTH(B10),1) -> 45748 | Q10: =IF(N10>Summary!$C$17,"Outlier","") | R10: =IF(L10="","None",L10) -> None
A11: ORD200009 | B11: 45251 | C11: C31946 | D11: Desk | E11: 4 | F11: 509.38 | G11: 102 Main St | H11: Credit Card | I11: Shipped | J11: TRK33478363 | K11: 6 | L11: SAVE10 | M11: Google | N11: 2037.52 | O11: =YEAR(B11) -> 2023 | P11: =DATE(YEAR(B11),MONTH(B11),1) -> 45231 | Q11: =IF(N11>Summary!$C$17,"Outlier","") | R11: =IF(L11="","None",L11) -> SAVE10
A12: ORD200010 | B12: 45289 | C12: C43443 | D12: Tablet | E12: 5 | F12: 625.97 | G12: 333 Main St | H12: Credit Card | I12: Returned | J12: TRK98859248 | K12: 9 | L12: WINTER15 | M12: Instagram | N12: 3129.85 | O12: =YEAR(B12) -> 2023 | P12: =DATE(YEAR(B12),MONTH(B12),1) -> 45261 | Q12: =IF(N12>Summary!$C$17,"Outlier","") | R12: =IF(L12="","None",L12) -> WINTER15
A13: ORD200011 | B13: 45339 | C13: C93861 | D13: Monitor | E13: 3 | F13: 49.14 | G13: 831 Main St | H13: Online | I13: Returned | J13: TRK48234646 | K13: 7 | L13: SAVE10 | M13: Email | N13: 147.42 | O13: =YEAR(B13) -> 2024 | P13: =DATE(YEAR(B13),MONTH(B13),1) -> 45323 | Q13: =IF(N13>Summary!$C$17,"Outlier","") | R13: =IF(L13="","None",L13) -> SAVE10
A14: ORD200012 | B14: 45580 | C14: C38785 | D14: Monitor | E14: 2 | F14: 180.5 | G14: 179 Main St | H14: Debit Card | I14: Pending | J14: TRK20419991 | K14: 6 | L14: FREESHIP | M14: Referral | N14: 361 | O14: =YEAR(B14) -> 2024 | P14: =DATE(YEAR(B14),MONTH(B14),1) -> 45566 | Q14: =IF(N14>Summary!$C$17,"Outlier","") | R14: =IF(L14="","None",L14) -> FREESHIP
A15: ORD200013 | B15: 45168 | C15: C88348 | D15: Laptop | E15: 3 | F15: 201.49 | G15: 903 Main St | H15: Credit Card | I15: Returned | J15: TRK81913874 | K15: 4 | L15: FREESHIP | M15: Facebook | N15: 604.47 | O15: =YEAR(B15) -> 2023 | P15: =DATE(YEAR(B15),MONTH(B15),1) -> 45139 | Q15: =IF(N15>Summary!$C$17,"Outlier","") | R15: =IF(L15="","None",L15) -> FREESHIP
A16: ORD200014 | B16: 45012 | C16: C98474 | D16: Tablet | E16: 2 | F16: 393.33 | G16: 980 Main St | H16: Debit Card | I16: Pending | J16: TRK79186539 | K16: 3 | L16: SAVE10 | M16: Instagram | N16: 786.66 | O16: =YEAR(B16) -> 2023 | P16: =DATE(YEAR(B16),MONTH(B16),1) -> 44986 | Q16: =IF(N16>Summary!$C$17,"Outlier","") | R16: =IF(L16="","None",L16) -> SAVE10
A17: ORD200015 | B17: 45124 | C17: C39416 | D17: Printer | E17: 1 | F17: 473.96 | G17: 942 Main St | H17: Cash | I17: Delivered | J17: TRK54930938 | K17: 3 | M17: Google | N17: 473.96 | O17: =YEAR(B17) -> 2023 | P17: =DATE(YEAR(B17),MONTH(B17),1) -> 45108 | Q17: =IF(N17>Summary!$C$17,"Outlier","") | R17: =IF(L17="","None",L17) -> None
A18: ORD200016 | B18: 44950 | C18: C28976 | D18: Printer | E18: 2 | F18: 533.81 | G18: 914 Main St | H18: Credit Card | I18: Pending | J18: TRK13194259 | K18: 3 | L18: FREESHIP | M18: Email | N18: 1067.62 | O18: =YEAR(B18) -> 2023 | P18: =DATE(YEAR(B18),MONTH(B18),1) -> 44927 | Q18: =IF(N18>Summary!$C$17,"Outlier","") | R18: =IF(L18="","None",L18) -> FREESHIP
A19: ORD200017 | B19: 45353 | C19: C60672 | D19: Tablet | E19: 1 | F19: 423.4 | G19: 382 Main St | H19: Debit Card | I19: Shipped | J19: TRK11972116 | K19: 3 | M19: Referral | N19: 423.4 | O19: =YEAR(B19) -> 2024 | P19: =DATE(YEAR(B19),MONTH(B19),1) -> 45352 | Q19: =IF(N19>Summary!$C$17,"Outlier","") | R19: =IF(L19="","None",L19) -> None
A20: ORD200018 | B20: 45742 | C20: C84329 | D20: Desk | E20: 1 | F20: 431.44 | G20: 891 Main St | H20: Gift Card | I20: Pending | J20: TRK65191045 | K20: 3 | L20: SAVE10 | M20: Facebook | N20: 431.44 | O20: =YEAR(B20) -> 2025 | P20: =DATE(YEAR(B20),MONTH(B20),1) -> 45717 | Q20: =IF(N20>Summary!$C$17,"Outlier","") | R20: =IF(L20="","None",L20) -> SAVE10
A21: ORD200019 | B21: 44949 | C21: C14552 | D21: Monitor | E21: 5 | F21: 224 | G21: 273 Main St | H21: Cash | I21: Returned | J21: TRK59101365 | K21: 9 | L21: SAVE10 | M21: Google | N21: 1120 | O21: =YEAR(B21) -> 2023 | P21: =DATE(YEAR(B21),MONTH(B21),1) -> 44927 | Q21: =IF(N21>Summary!$C$17,"Outlier","") | R21: =IF(L21="","None",L21) -> SAVE10
A22: ORD200020 | B22: 45054 | C22: C54829 | D22: Chair | E22: 5 | F22: 62.51 | G22: 587 Main St | H22: Cash | I22: Pending | J22: TRK16718651 | K22: 9 | L22: WINTER15 | M22: Instagram | N22: 312.55 | O22: =YEAR(B22) -> 2023 | P22: =DATE(YEAR(B22),MONTH(B22),1) -> 45047 | Q22: =IF(N22>Summary!$C$17,"Outlier","") | R22: =IF(L22="","None",L22) -> WINTER15
A23: ORD200021 | B23: 45613 | C23: C99023 | D23: Monitor | E23: 4 | F23: 342.95 | G23: 569 Main St | H23: Cash | I23: Delivered | J23: TRK52646983 | K23: 6 | M23: Google | N23: 1371.8 | O23: =YEAR(B23) -> 2024 | P23: =DATE(YEAR(B23),MONTH(B23),1) -> 45597 | Q23: =IF(N23>Summary!$C$17,"Outlier","") | R23: =IF(L23="","None",L23) -> None
A24: ORD200022 | B24: 44955 | C24: C34416 | D24: Monitor | E24: 2 | F24: 49.62 | G24: 633 Main St | H24: Online | I24: Pending | J24: TRK75937350 | K24: 2 | L24: SAVE10 | M24: Google | N24: 99.24 | O24: =YEAR(B24) -> 2023 | P24: =DATE(YEAR(B24),MONTH(B24),1) -> 44927 | Q24: =IF(N24>Summary!$C$17,"Outlier","") | R24: =IF(L24="","None",L24) -> SAVE10
A25: ORD200023 | B25: 45756 | C25: C42372 | D25: Phone | E25: 4 | F25: 273.25 | G25: 755 Main St | H25: Debit Card | I25: Cancelled | J25: TRK36168083 | K25: 5 | L25: FREESHIP | M25: Referral | N25: 1093 | O25: =YEAR(B25) -> 2025 | P25: =DATE(YEAR(B25),MONTH(B25),1) -> 45748 | Q25: =IF(N25>Summary!$C$17,"Outlier","") | R25: =IF(L25="","None",L25) -> FREESHIP
A26: ORD200024 | B26: 45595 | C26: C17470 | D26: Laptop | E26: 2 | F26: 230.95 | G26: 956 Main St | H26: Online | I26: Delivered | J26: TRK28775057 | K26: 3 | L26: WINTER15 | M26: Referral | N26: 461.9 | O26: =YEAR(B26) -> 2024 | P26: =DATE(YEAR(B26),MONTH(B26),1) -> 45566 | Q26: =IF(N26>Summary!$C$17,"Outlier","") | R26: =IF(L26="","None",L26) -> WINTER15
A27: ORD200025 | B27: 45497 | C27: C42577 | D27: Monitor | E27: 1 | F27: 399.98 | G27: 709 Main St | H27: Debit Card | I27: Delivered | J27: TRK69423327 | K27: 3 | L27: WINTER15 | M27: Email | N27: 399.98 | O27: =YEAR(B27) -> 2024 | P27: =DATE(YEAR(B27),MONTH(B27),1) -> 45474 | Q27: =IF(N27>Summary!$C$17,"Outlier","") | R27: =IF(L27="","None",L27) -> WINTER15
A28: ORD200026 | B28: 45357 | C28: C21944 | D28: Laptop | E28: 5 | F28: 59.55 | G28: 296 Main St | H28: Online | I28: Delivered | J28: TRK80276812 | K28: 6 | M28: Referral | N28: 297.75 | O28: =YEAR(B28) -> 2024 | P28: =DATE(YEAR(B28),MONTH(B28),1) -> 45352 | Q28: =IF(N28>Summary!$C$17,"Outlier","") | R28: =IF(L28="","None",L28) -> None
A29: ORD200027 | B29: 45344 | C29: C97593 | D29: Printer | E29: 1 | F29: 472.74 | G29: 881 Main St | H29: Online | I29: Shipped | J29: TRK89117573 | K29: 6 | L29: WINTER15 | M29: Google | N29: 472.74 | O29: =YEAR(B29) -> 2024 | P29: =DATE(YEAR(B29),MONTH(B29),1) -> 45323 | Q29: =IF(N29>Summary!$C$17,"Outlier","") | R29: =IF(L29="","None",L29) -> WINTER15
A30: ORD200028 | B30: 45251 | C30: C59823 | D30: Phone | E30: 4 | F30: 160.07 | G30: 568 Main St | H30: Online | I30: Pending | J30: TRK65895539 | K30: 5 | M30: Email | N30: 640.28 | O30: =YEAR(B30) -> 2023 | P30: =DATE(YEAR(B30),MONTH(B30),1) -> 45231 | Q30: =IF(N30>Summary!$C$17,"Outlier","") | R30: =IF(L30="","None",L30) -> None
A31: ORD200029 | B31: 45555 | C31: C33260 | D31: Desk | E31: 3 | F31: 423.53 | G31: 930 Main St | H31: Credit Card | I31: Delivered | J31: TRK59744090 | K31: 6 | L31: SAVE10 | M31: Referral | N31: 1270.59 | O31: =YEAR(B31) -> 2024 | P31: =DATE(YEAR(B31),MONTH(B31),1) -> 45536 | Q31: =IF(N31>Summary!$C$17,"Outlier","") | R31: =IF(L31="","None",L31) -> SAVE10
A32: ORD200030 | B32: 45738 | C32: C44267 | D32: Monitor | E32: 2 | F32: 426.7 | G32: 895 Main St | H32: Online | I32: Pending | J32: TRK54751444 | K32: 5 | L32: SAVE10 | M32: Referral | N32: 853.4 | O32: =YEAR(B32) -> 2025 | P32: =DATE(YEAR(B32),MONTH(B32),1) -> 45717 | Q32: =IF(N32>Summary!$C$17,"Outlier","") | R32: =IF(L32="","None",L32) -> SAVE10
A33: ORD200031 | B33: 45107 | C33: C26445 | D33: Chair | E33: 3 | F33: 500.08 | G33: 996 Main St | H33: Debit Card | I33: Returned | J33: TRK31229981 | K33: 6 | M33: Facebook | N33: 1500.24 | O33: =YEAR(B33) -> 2023 | P33: =DATE(YEAR(B33),MONTH(B33),1) -> 45078 | Q33: =IF(N33>Summary!$C$17,"Outlier","") | R33: =IF(L33="","None",L33) -> None
A34: ORD200032 | B34: 45047 | C34: C12388 | D34: Tablet | E34: 5 | F34: 536.72 | G34: 830 Main St | H34: Cash | I34: Delivered | J34: TRK99261395 | K34: 10 | M34: Email | N34: 2683.6 | O34: =YEAR(B34) -> 2023 | P34: =DATE(YEAR(B34),MONTH(B34),1) -> 45047 | Q34: =IF(N34>Summary!$C$17,"Outlier","") | R34: =IF(L34="","None",L34) -> None
A35: ORD200033 | B35: 45082 | C35: C52184 | D35: Chair | E35: 1 | F35: 162.77 | G35: 912 Main St | H35: Online | I35: Cancelled | J35: TRK73312471 | K35: 4 | L35: WINTER15 | M35: Facebook | N35: 162.77 | O35: =YEAR(B35) -> 2023 | P35: =DATE(YEAR(B35),MONTH(B35),1) -> 45078 | Q35: =IF(N35>Summary!$C$17,"Outlier","") | R35: =IF(L35="","None",L35) -> WINTER15
A36: ORD200034 | B36: 44933 | C36: C67195 | D36: Chair | E36: 4 | F36: 576.52 | G36: 926 Main St | H36: Credit Card | I36: Pending | J36: TRK55467915 | K36: 5 | L36: WINTER15 | M36: Facebook | N36: 2306.08 | O36: =YEAR(B36) -> 2023 | P36: =DATE(YEAR(B36),MONTH(B36),1) -> 44927 | Q36: =IF(N36>Summary!$C$17,"Outlier","") | R36: =IF(L36="","None",L36) -> WINTER15
A37: ORD200035 | B37: 45633 | C37: C50304 | D37: Monitor | E37: 2 | F37: 465.15 | G37: 128 Main St | H37: Online | I37: Shipped | J37: TRK46850888 | K37: 2 | L37: SAVE10 | M37: Facebook | N37: 930.3 | O37: =YEAR(B37) -> 2024 | P37: =DATE(YEAR(B37),MONTH(B37),1) -> 45627 | Q37: =IF(N37>Summary!$C$17,"Outlier","") | R37: =IF(L37="","None",L37) -> SAVE10
A38: ORD200036 | B38: 45785 | C38: C59337 | D38: Laptop | E38: 2 | F38: 534.43 | G38: 465 Main St | H38: Debit Card | I38: Pending | J38: TRK50961250 | K38: 5 | M38: Facebook | N38: 1068.86 | O38: =YEAR(B38) -> 2025 | P38: =DATE(YEAR(B38),MONTH(B38),1) -> 45778 | Q38: =IF(N38>Summary!$C$17,"Outlier","") | R38: =IF(L38="","None",L38) -> None
A39: ORD200037 | B39: 45579 | C39: C10054 | D39: Laptop | E39: 2 | F39: 76.74 | G39: 409 Main St | H39: Cash | I39: Returned | J39: TRK94005261 | K39: 7 | L39: SAVE10 | M39: Instagram | N39: 153.48 | O39: =YEAR(B39) -> 2024 | P39: =DATE(YEAR(B39),MONTH(B39),1) -> 45566 | Q39: =IF(N39>Summary!$C$17,"Outlier","") | R39: =IF(L39="","None",L39) -> SAVE10
A40: ORD200038 | B40: 45645 | C40: C15924 | D40: Laptop | E40: 1 | F40: 245.89 | G40: 549 Main St | H40: Debit Card | I40: Delivered | J40: TRK14835975 | K40: 3 | L40: SAVE10 | M40: Google | N40: 245.89 | O40: =YEAR(B40) -> 2024 | P40: =DATE(YEAR(B40),MONTH(B40),1) -> 45627 | Q40: =IF(N40>Summary!$C$17,"Outlier","") | R40: =IF(L40="","None",L40) -> SAVE10
A41: ORD200039 | B41: 45715 | C41: C96664 | D41: Printer | E41: 3 | F41: 256.46 | G41: 666 Main St | H41: Credit Card | I41: Delivered | J41: TRK85508960 | K41: 4 | L41: SAVE10 | M41: Referral | N41: 769.38 | O41: =YEAR(B41) -> 2025 | P41: =DATE(YEAR(B41),MONTH(B41),1) -> 45689 | Q41: =IF(N41>Summary!$C$17,"Outlier","") | R41: =IF(L41="","None",L41) -> SAVE10
A42: ORD200040 | B42: 45158 | C42: C84766 | D42: Desk | E42: 2 | F42: 344.02 | G42: 267 Main St | H42: Online | I42: Delivered | J42: TRK78967923 | K42: 4 | L42: FREESHIP | M42: Instagram | N42: 688.04 | O42: =YEAR(B42) -> 2023 | P42: =DATE(YEAR(B42),MONTH(B42),1) -> 45139 | Q42: =IF(N42>Summary!$C$17,"Outlier","") | R42: =IF(L42="","None",L42) -> FREESHIP
A43: ORD200041 | B43: 45265 | C43: C20212 | D43: Monitor | E43: 3 | F43: 611.45 | G43: 657 Main St | H43: Gift Card | I43: Pending | J43: TRK69733327 | K43: 4 | L43: FREESHIP | M43: Instagram | N43: 1834.35 | O43: =YEAR(B43) -> 2023 | P43: =DATE(YEAR(B43),MONTH(B43),1) -> 45261 | Q43: =IF(N43>Summary!$C$17,"Outlier","") | R43: =IF(L43="","None",L43) -> FREESHIP
A44: ORD200042 | B44: 45418 | C44: C28712 | D44: Printer | E44: 2 | F44: 151.66 | G44: 980 Main St | H44: Cash | I44: Cancelled | J44: TRK40772558 | K44: 6 | M44: Instagram | N44: 303.32 | O44: =YEAR(B44) -> 2024 | P44: =DATE(YEAR(B44),MONTH(B44),1) -> 45413 | Q44: =IF(N44>Summary!$C$17,"Outlier","") | R44: =IF(L44="","None",L44) -> None
A45: ORD200043 | B45: 45274 | C45: C60572 | D45: Chair | E45: 3 | F45: 499.21 | G45: 871 Main St | H45: Online | I45: Cancelled | J45: TRK20351666 | K45: 8 | M45: Instagram | N45: 1497.63 | O45: =YEAR(B45) -> 2023 | P45: =DATE(YEAR(B45),MONTH(B45),1) -> 45261 | Q45: =IF(N45>Summary!$C$17,"Outlier","") | R45: =IF(L45="","None",L45) -> None
A46: ORD200044 | B46: 45768 | C46: C73225 | D46: Phone | E46: 2 | F46: 550.18 | G46: 996 Main St | H46: Gift Card | I46: Returned | J46: TRK73848522 | K46: 3 | L46: FREESHIP | M46: Referral | N46: 1100.36 | O46: =YEAR(B46) -> 2025 | P46: =DATE(YEAR(B46),MONTH(B46),1) -> 45748 | Q46: =IF(N46>Summary!$C$17,"Outlier","") | R46: =IF(L46="","None",L46) -> FREESHIP
A47: ORD200045 | B47: 45332 | C47: C17388 | D47: Chair | E47: 1 | F47: 317.25 | G47: 157 Main St | H47: Debit Card | I47: Returned | J47: TRK47077395 | K47: 1 | L47: SAVE10 | M47: Facebook | N47: 317.25 | O47: =YEAR(B47) -> 2024 | P47: =DATE(YEAR(B47),MONTH(B47),1) -> 45323 | Q47: =IF(N47>Summary!$C$17,"Outlier","") | R47: =IF(L47="","None",L47) -> SAVE10
A48: ORD200046 | B48: 45469 | C48: C43212 | D48: Monitor | E48: 4 | F48: 550.14 | G48: 223 Main St | H48: Debit Card | I48: Pending | J48: TRK25100762 | K48: 4 | L48: FREESHIP | M48: Instagram | N48: 2200.56 | O48: =YEAR(B48) -> 2024 | P48: =DATE(YEAR(B48),MONTH(B48),1) -> 45444 | Q48: =IF(N48>Summary!$C$17,"Outlier","") | R48: =IF(L48="","None",L48) -> FREESHIP
A49: ORD200047 | B49: 45126 | C49: C38134 | D49: Desk | E49: 2 | F49: 209.94 | G49: 323 Main St | H49: Credit Card | I49: Returned | J49: TRK42450754 | K49: 3 | L49: FREESHIP | M49: Email | N49: 419.88 | O49: =YEAR(B49) -> 2023 | P49: =DATE(YEAR(B49),MONTH(B49),1) -> 45108 | Q49: =IF(N49>Summary!$C$17,"Outlier","") | R49: =IF(L49="","None",L49) -> FREESHIP
A50: ORD200048 | B50: 45164 | C50: C12408 | D50: Monitor | E50: 2 | F50: 80.77 | G50: 464 Main St | H50: Debit Card | I50: Shipped | J50: TRK38938858 | K50: 4 | M50: Google | N50: 161.54 | O50: =YEAR(B50) -> 2023 | P50: =DATE(YEAR(B50),MONTH(B50),1) -> 45139 | Q50: =IF(N50>Summary!$C$17,"Outlier","") | R50: =IF(L50="","None",L50) -> None
A51: ORD200049 | B51: 45206 | C51: C11985 | D51: Printer | E51: 1 | F51: 30.44 | G51: 633 Main St | H51: Credit Card | I51: Shipped | J51: TRK53272402 | K51: 1 | L51: SAVE10 | M51: Email | N51: 30.44 | O51: =YEAR(B51) -> 2023 | P51: =DATE(YEAR(B51),MONTH(B51),1) -> 45200 | Q51: =IF(N51>Summary!$C$17,"Outlier","") | R51: =IF(L51="","None",L51) -> SAVE10
A52: ORD200050 | B52: 45138 | C52: C96494 | D52: Tablet | E52: 1 | F52: 179.22 | G52: 446 Main St | H52: Online | I52: Cancelled | J52: TRK14675049 | K52: 6 | L52: FREESHIP | M52: Instagram | N52: 179.22 | O52: =YEAR(B52) -> 2023 | P52: =DATE(YEAR(B52),MONTH(B52),1) -> 45108 | Q52: =IF(N52>Summary!$C$17,"Outlier","") | R52: =IF(L52="","None",L52) -> FREESHIP
A53: ORD200051 | B53: 45656 | C53: C36778 | D53: Tablet | E53: 1 | F53: 388.33 | G53: 434 Main St | H53: Cash | I53: Returned | J53: TRK67610289 | K53: 2 | L53: SAVE10 | M53: Facebook | N53: 388.33 | O53: =YEAR(B53) -> 2024 | P53: =DATE(YEAR(B53),MONTH(B53),1) -> 45627 | Q53: =IF(N53>Summary!$C$17,"Outlier","") | R53: =IF(L53="","None",L53) -> SAVE10
A54: ORD200052 | B54: 45543 | C54: C30513 | D54: Tablet | E54: 1 | F54: 586.44 | G54: 232 Main St | H54: Online | I54: Returned | J54: TRK64320429 | K54: 5 | L54: SAVE10 | M54: Facebook | N54: 586.44 | O54: =YEAR(B54) -> 2024 | P54: =DATE(YEAR(B54),MONTH(B54),1) -> 45536 | Q54: =IF(N54>Summary!$C$17,"Outlier","") | R54: =IF(L54="","None",L54) -> SAVE10
A55: ORD200053 | B55: 45430 | C55: C67551 | D55: Phone | E55: 4 | F55: 488.78 | G55: 512 Main St | H55: Online | I55: Returned | J55: TRK94992552 | K55: 5 | L55: FREESHIP | M55: Google | N55: 1955.12 | O55: =YEAR(B55) -> 2024 | P55: =DATE(YEAR(B55),MONTH(B55),1) -> 45413 | Q55: =IF(N55>Summary!$C$17,"Outlier","") | R55: =IF(L55="","None",L55) -> FREESHIP
A56: ORD200054 | B56: 45743 | C56: C48120 | D56: Chair | E56: 1 | F56: 280.25 | G56: 623 Main St | H56: Online | I56: Pending | J56: TRK11014449 | K56: 5 | L56: WINTER15 | M56: Email | N56: 280.25 | O56: =YEAR(B56) -> 2025 | P56: =DATE(YEAR(B56),MONTH(B56),1) -> 45717 | Q56: =IF(N56>Summary!$C$17,"Outlier","") | R56: =IF(L56="","None",L56) -> WINTER15
A57: ORD200055 | B57: 45832 | C57: C95984 | D57: Printer | E57: 3 | F57: 344.4 | G57: 565 Main St | H57: Online | I57: Cancelled | J57: TRK67434829 | K57: 3 | M57: Facebook | N57: 1033.2 | O57: =YEAR(B57) -> 2025 | P57: =DATE(YEAR(B57),MONTH(B57),1) -> 45809 | Q57: =IF(N57>Summary!$C$17,"Outlier","") | R57: =IF(L57="","None",L57) -> None
A58: ORD200056 | B58: 45067 | C58: C54298 | D58: Tablet | E58: 3 | F58: 479.21 | G58: 566 Main St | H58: Cash | I58: Cancelled | J58: TRK62902341 | K58: 5 | L58: WINTER15 | M58: Referral | N58: 1437.63 | O58: =YEAR(B58) -> 2023 | P58: =DATE(YEAR(B58),MONTH(B58),1) -> 45047 | Q58: =IF(N58>Summary!$C$17,"Outlier","") | R58: =IF(L58="","None",L58) -> WINTER15
A59: ORD200057 | B59: 44948 | C59: C88036 | D59: Printer | E59: 5 | F59: 314.27 | G59: 842 Main St | H59: Cash | I59: Returned | J59: TRK52470128 | K59: 6 | L59: SAVE10 | M59: Instagram | N59: 1571.35 | O59: =YEAR(B59) -> 2023 | P59: =DATE(YEAR(B59),MONTH(B59),1) -> 44927 | Q59: =IF(N59>Summary!$C$17,"Outlier","") | R59: =IF(L59="","None",L59) -> SAVE10
A60: ORD200058 | B60: 44941 | C60: C60190 | D60: Phone | E60: 4 | F60: 474.69 | G60: 202 Main St | H60: Gift Card | I60: Cancelled | J60: TRK70857868 | K60: 6 | L60: SAVE10 | M60: Google | N60: 1898.76 | O60: =YEAR(B60) -> 2023 | P60: =DATE(YEAR(B60),MONTH(B60),1) -> 44927 | Q60: =IF(N60>Summary!$C$17,"Outlier","") | R60: =IF(L60="","None",L60) -> SAVE10
A61: ORD200059 | B61: 45546 | C61: C97603 | D61: Chair | E61: 4 | F61: 593.27 | G61: 811 Main St | H61: Online | I61: Shipped | J61: TRK47055028 | K61: 5 | M61: Facebook | N61: 2373.08 | O61: =YEAR(B61) -> 2024 | P61: =DATE(YEAR(B61),MONTH(B61),1) -> 45536 | Q61: =IF(N61>Summary!$C$17,"Outlier","") | R61: =IF(L61="","None",L61) -> None
A62: ORD200060 | B62: 45525 | C62: C39256 | D62: Desk | E62: 1 | F62: 417.1 | G62: 634 Main St | H62: Debit Card | I62: Returned | J62: TRK23412025 | K62: 3 | L62: FREESHIP | M62: Referral | N62: 417.1 | O62: =YEAR(B62) -> 2024 | P62: =DATE(YEAR(B62),MONTH(B62),1) -> 45505 | Q62: =IF(N62>Summary!$C$17,"Outlier","") | R62: =IF(L62="","None",L62) -> FREESHIP
A63: ORD200061 | B63: 45375 | C63: C61618 | D63: Desk | E63: 4 | F63: 122.2 | G63: 104 Main St | H63: Cash | I63: Delivered | J63: TRK43458485 | K63: 7 | L63: FREESHIP | M63: Facebook | N63: 488.8 | O63: =YEAR(B63) -> 2024 | P63: =DATE(YEAR(B63),MONTH(B63),1) -> 45352 | Q63: =IF(N63>Summary!$C$17,"Outlier","") | R63: =IF(L63="","None",L63) -> FREESHIP
A64: ORD200062 | B64: 45160 | C64: C36497 | D64: Desk | E64: 2 | F64: 43.15 | G64: 691 Main St | H64: Debit Card | I64: Pending | J64: TRK12102911 | K64: 3 | L64: WINTER15 | M64: Email | N64: 86.3 | O64: =YEAR(B64) -> 2023 | P64: =DATE(YEAR(B64),MONTH(B64),1) -> 45139 | Q64: =IF(N64>Summary!$C$17,"Outlier","") | R64: =IF(L64="","None",L64) -> WINTER15
A65: ORD200063 | B65: 45690 | C65: C96695 | D65: Chair | E65: 1 | F65: 564.86 | G65: 813 Main St | H65: Debit Card | I65: Shipped | J65: TRK64283851 | K65: 6 | L65: WINTER15 | M65: Referral | N65: 564.86 | O65: =YEAR(B65) -> 2025 | P65: =DATE(YEAR(B65),MONTH(B65),1) -> 45689 | Q65: =IF(N65>Summary!$C$17,"Outlier","") | R65: =IF(L65="","None",L65) -> WINTER15
A66: ORD200064 | B66: 45833 | C66: C49720 | D66: Printer | E66: 3 | F66: 130.61 | G66: 752 Main St | H66: Debit Card | I66: Cancelled | J66: TRK55785217 | K66: 4 | L66: FREESHIP | M66: Facebook | N66: 391.83 | O66: =YEAR(B66) -> 2025 | P66: =DATE(YEAR(B66),MONTH(B66),1) -> 45809 | Q66: =IF(N66>Summary!$C$17,"Outlier","") | R66: =IF(L66="","None",L66) -> FREESHIP
A67: ORD200065 | B67: 45290 | C67: C97735 | D67: Monitor | E67: 5 | F67: 81.7 | G67: 385 Main St | H67: Credit Card | I67: Delivered | J67: TRK13743703 | K67: 6 | M67: Instagram | N67: 408.5 | O67: =YEAR(B67) -> 2023 | P67: =DATE(YEAR(B67),MONTH(B67),1) -> 45261 | Q67: =IF(N67>Summary!$C$17,"Outlier","") | R67: =IF(L67="","None",L67) -> None
A68: ORD200066 | B68: 45611 | C68: C18104 | D68: Chair | E68: 5 | F68: 127.18 | G68: 715 Main St | H68: Cash | I68: Cancelled | J68: TRK15488568 | K68: 9 | L68: SAVE10 | M68: Referral | N68: 635.9 | O68: =YEAR(B68) -> 2024 | P68: =DATE(YEAR(B68),MONTH(B68),1) -> 45597 | Q68: =IF(N68>Summary!$C$17,"Outlier","") | R68: =IF(L68="","None",L68) -> SAVE10
A69: ORD200067 | B69: 45635 | C69: C25587 | D69: Printer | E69: 4 | F69: 12.1 | G69: 440 Main St | H69: Debit Card | I69: Cancelled | J69: TRK55105323 | K69: 8 | M69: Google | N69: 48.4 | O69: =YEAR(B69) -> 2024 | P69: =DATE(YEAR(B69),MONTH(B69),1) -> 45627 | Q69: =IF(N69>Summary!$C$17,"Outlier","") | R69: =IF(L69="","None",L69) -> None
A70: ORD200068 | B70: 45271 | C70: C41598 | D70: Chair | E70: 3 | F70: 490.92 | G70: 709 Main St | H70: Credit Card | I70: Pending | J70: TRK81665940 | K70: 5 | L70: FREESHIP | M70: Email | N70: 1472.76 | O70: =YEAR(B70) -> 2023 | P70: =DATE(YEAR(B70),MONTH(B70),1) -> 45261 | Q70: =IF(N70>Summary!$C$17,"Outlier","") | R70: =IF(L70="","None",L70) -> FREESHIP
A71: ORD200069 | B71: 45057 | C71: C43338 | D71: Monitor | E71: 3 | F71: 478.65 | G71: 552 Main St | H71: Online | I71: Shipped | J71: TRK35241775 | K71: 4 | M71: Referral | N71: 1435.95 | O71: =YEAR(B71) -> 2023 | P71: =DATE(YEAR(B71),MONTH(B71),1) -> 45047 | Q71: =IF(N71>Summary!$C$17,"Outlier","") | R71: =IF(L71="","None",L71) -> None
A72: ORD200070 | B72: 45072 | C72: C25123 | D72: Desk | E72: 1 | F72: 629.21 | G72: 384 Main St | H72: Gift Card | I72: Pending | J72: TRK27812282 | K72: 2 | L72: FREESHIP | M72: Instagram | N72: 629.21 | O72: =YEAR(B72) -> 2023 | P72: =DATE(YEAR(B72),MONTH(B72),1) -> 45047 | Q72: =IF(N72>Summary!$C$17,"Outlier","") | R72: =IF(L72="","None",L72) -> FREESHIP
A73: ORD200071 | B73: 45818 | C73: C37454 | D73: Monitor | E73: 3 | F73: 434.45 | G73: 923 Main St | H73: Credit Card | I73: Pending | J73: TRK28252730 | K73: 4 | M73: Referral | N73: 1303.35 | O73: =YEAR(B73) -> 2025 | P73: =DATE(YEAR(B73),MONTH(B73),1) -> 45809 | Q73: =IF(N73>Summary!$C$17,"Outlier","") | R73: =IF(L73="","None",L73) -> None
A74: ORD200072 | B74: 45648 | C74: C19451 | D74: Tablet | E74: 4 | F74: 589.44 | G74: 942 Main St | H74: Gift Card | I74: Returned | J74: TRK87787793 | K74: 5 | M74: Facebook | N74: 2357.76 | O74: =YEAR(B74) -> 2024 | P74: =DATE(YEAR(B74),MONTH(B74),1) -> 45627 | Q74: =IF(N74>Summary!$C$17,"Outlier","") | R74: =IF(L74="","None",L74) -> None
A75: ORD200073 | B75: 45049 | C75: C17269 | D75: Monitor | E75: 4 | F75: 433.45 | G75: 129 Main St | H75: Gift Card | I75: Cancelled | J75: TRK79608389 | K75: 4 | M75: Facebook | N75: 1733.8 | O75: =YEAR(B75) -> 2023 | P75: =DATE(YEAR(B75),MONTH(B75),1) -> 45047 | Q75: =IF(N75>Summary!$C$17,"Outlier","") | R75: =IF(L75="","None",L75) -> None
A76: ORD200074 | B76: 45101 | C76: C25382 | D76: Phone | E76: 5 | F76: 90.87 | G76: 622 Main St | H76: Cash | I76: Pending | J76: TRK64691287 | K76: 5 | M76: Instagram | N76: 454.35 | O76: =YEAR(B76) -> 2023 | P76: =DATE(YEAR(B76),MONTH(B76),1) -> 45078 | Q76: =IF(N76>Summary!$C$17,"Outlier","") | R76: =IF(L76="","None",L76) -> None
A77: ORD200075 | B77: 45195 | C77: C80651 | D77: Tablet | E77: 3 | F77: 398.17 | G77: 917 Main St | H77: Debit Card | I77: Delivered | J77: TRK14846720 | K77: 5 | L77: SAVE10 | M77: Email | N77: 1194.51 | O77: =YEAR(B77) -> 2023 | P77: =DATE(YEAR(B77),MONTH(B77),1) -> 45170 | Q77: =IF(N77>Summary!$C$17,"Outlier","") | R77: =IF(L77="","None",L77) -> SAVE10
A78: ORD200076 | B78: 45382 | C78: C58638 | D78: Laptop | E78: 4 | F78: 382.88 | G78: 239 Main St | H78: Cash | I78: Cancelled | J78: TRK38224871 | K78: 6 | L78: WINTER15 | M78: Email | N78: 1531.52 | O78: =YEAR(B78) -> 2024 | P78: =DATE(YEAR(B78),MONTH(B78),1) -> 45352 | Q78: =IF(N78>Summary!$C$17,"Outlier","") | R78: =IF(L78="","None",L78) -> WINTER15
A79: ORD200077 | B79: 45436 | C79: C50121 | D79: Phone | E79: 1 | F79: 583.18 | G79: 348 Main St | H79: Credit Card | I79: Returned | J79: TRK79810059 | K79: 5 | M79: Google | N79: 583.18 | O79: =YEAR(B79) -> 2024 | P79: =DATE(YEAR(B79),MONTH(B79),1) -> 45413 | Q79: =IF(N79>Summary!$C$17,"Outlier","") | R79: =IF(L79="","None",L79) -> None
A80: ORD200078 | B80: 45510 | C80: C32029 | D80: Printer | E80: 4 | F80: 175.36 | G80: 146 Main St | H80: Debit Card | I80: Delivered | J80: TRK68535532 | K80: 4 | L80: FREESHIP | M80: Instagram | N80: 701.44 | O80: =YEAR(B80) -> 2024 | P80: =DATE(YEAR(B80),MONTH(B80),1) -> 45505 | Q80: =IF(N80>Summary!$C$17,"Outlier","") | R80: =IF(L80="","None",L80) -> FREESHIP
A81: ORD200079 | B81: 45726 | C81: C76700 | D81: Tablet | E81: 2 | F81: 311.91 | G81: 103 Main St | H81: Online | I81: Shipped | J81: TRK13036341 | K81: 2 | M81: Facebook | N81: 623.82 | O81: =YEAR(B81) -> 2025 | P81: =DATE(YEAR(B81),MONTH(B81),1) -> 45717 | Q81: =IF(N81>Summary!$C$17,"Outlier","") | R81: =IF(L81="","None",L81) -> None
A82: ORD200080 | B82: 45104 | C82: C29041 | D82: Phone | E82: 3 | F82: 589.56 | G82: 591 Main St | H82: Online | I82: Returned | J82: TRK28840655 | K82: 6 | M82: Facebook | N82: 1768.68 | O82: =YEAR(B82) -> 2023 | P82: =DATE(YEAR(B82),MONTH(B82),1) -> 45078 | Q82: =IF(N82>Summary!$C$17,"Outlier","") | R82: =IF(L82="","None",L82) -> None
A83: ORD200081 | B83: 45085 | C83: C29314 | D83: Monitor | E83: 2 | F83: 394.3 | G83: 496 Main St | H83: Cash | I83: Shipped | J83: TRK59876213 | K83: 6 | L83: FREESHIP | M83: Email | N83: 788.6 | O83: =YEAR(B83) -> 2023 | P83: =DATE(YEAR(B83),MONTH(B83),1) -> 45078 | Q83: =IF(N83>Summary!$C$17,"Outlier","") | R83: =IF(L83="","None",L83) -> FREESHIP
A84: ORD200082 | B84: 45296 | C84: C65799 | D84: Tablet | E84: 4 | F84: 565.2 | G84: 971 Main St | H84: Debit Card | I84: Shipped | J84: TRK66906607 | K84: 9 | L84: SAVE10 | M84: Google | N84: 2260.8 | O84: =YEAR(B84) -> 2024 | P84: =DATE(YEAR(B84),MONTH(B84),1) -> 45292 | Q84: =IF(N84>Summary!$C$17,"Outlier","") | R84: =IF(L84="","None",L84) -> SAVE10
A85: ORD200083 | B85: 45160 | C85: C15681 | D85: Laptop | E85: 4 | F85: 540.41 | G85: 989 Main St | H85: Credit Card | I85: Cancelled | J85: TRK75112172 | K85: 6 | M85: Referral | N85: 2161.64 | O85: =YEAR(B85) -> 2023 | P85: =DATE(YEAR(B85),MONTH(B85),1) -> 45139 | Q85: =IF(N85>Summary!$C$17,"Outlier","") | R85: =IF(L85="","None",L85) -> None
A86: ORD200084 | B86: 45166 | C86: C64160 | D86: Monitor | E86: 2 | F86: 165.49 | G86: 967 Main St | H86: Online | I86: Shipped | J86: TRK34121529 | K86: 4 | L86: WINTER15 | M86: Instagram | N86: 330.98 | O86: =YEAR(B86) -> 2023 | P86: =DATE(YEAR(B86),MONTH(B86),1) -> 45139 | Q86: =IF(N86>Summary!$C$17,"Outlier","") | R86: =IF(L86="","None",L86) -> WINTER15
A87: ORD200085 | B87: 45544 | C87: C14553 | D87: Tablet | E87: 3 | F87: 146.73 | G87: 768 Main St | H87: Cash | I87: Delivered | J87: TRK93538334 | K87: 8 | L87: FREESHIP | M87: Email | N87: 440.19 | O87: =YEAR(B87) -> 2024 | P87: =DATE(YEAR(B87),MONTH(B87),1) -> 45536 | Q87: =IF(N87>Summary!$C$17,"Outlier","") | R87: =IF(L87="","None",L87) -> FREESHIP
A88: ORD200086 | B88: 45462 | C88: C88205 | D88: Printer | E88: 5 | F88: 643.03 | G88: 447 Main St | H88: Online | I88: Cancelled | J88: TRK93504166 | K88: 5 | L88: FREESHIP | M88: Referral | N88: 3215.15 | O88: =YEAR(B88) -> 2024 | P88: =DATE(YEAR(B88),MONTH(B88),1) -> 45444 | Q88: =IF(N88>Summary!$C$17,"Outlier","") | R88: =IF(L88="","None",L88) -> FREESHIP
A89: ORD200087 | B89: 45575 | C89: C91245 | D89: Tablet | E89: 3 | F89: 225.11 | G89: 915 Main St | H89: Cash | I89: Shipped | J89: TRK46976391 | K89: 4 | L89: SAVE10 | M89: Facebook | N89: 675.33 | O89: =YEAR(B89) -> 2024 | P89: =DATE(YEAR(B89),MONTH(B89),1) -> 45566 | Q89: =IF(N89>Summary!$C$17,"Outlier","") | R89: =IF(L89="","None",L89) -> SAVE10
A90: ORD200088 | B90: 45813 | C90: C75439 | D90: Desk | E90: 3 | F90: 114.81 | G90: 318 Main St | H90: Gift Card | I90: Cancelled | J90: TRK19831653 | K90: 7 | M90: Google | N90: 344.43 | O90: =YEAR(B90) -> 2025 | P90: =DATE(YEAR(B90),MONTH(B90),1) -> 45809 | Q90: =IF(N90>Summary!$C$17,"Outlier","") | R90: =IF(L90="","None",L90) -> None
A91: ORD200089 | B91: 45713 | C91: C17181 | D91: Printer | E91: 5 | F91: 455.33 | G91: 291 Main St | H91: Credit Card | I91: Cancelled | J91: TRK78912978 | K91: 8 | L91: FREESHIP | M91: Google | N91: 2276.65 | O91: =YEAR(B91) -> 2025 | P91: =DATE(YEAR(B91),MONTH(B91),1) -> 45689 | Q91: =IF(N91>Summary!$C$17,"Outlier","") | R91: =IF(L91="","None",L91) -> FREESHIP
A92: ORD200090 | B92: 45187 | C92: C36540 | D92: Chair | E92: 4 | F92: 182.08 | G92: 611 Main St | H92: Gift Card | I92: Delivered | J92: TRK35828122 | K92: 4 | L92: SAVE10 | M92: Email | N92: 728.32 | O92: =YEAR(B92) -> 2023 | P92: =DATE(YEAR(B92),MONTH(B92),1) -> 45170 | Q92: =IF(N92>Summary!$C$17,"Outlier","") | R92: =IF(L92="","None",L92) -> SAVE10
A93: ORD200091 | B93: 45000 | C93: C98216 | D93: Laptop | E93: 5 | F93: 492.75 | G93: 196 Main St | H93: Cash | I93: Shipped | J93: TRK40986666 | K93: 6 | L93: WINTER15 | M93: Referral | N93: 2463.75 | O93: =YEAR(B93) -> 2023 | P93: =DATE(YEAR(B93),MONTH(B93),1) -> 44986 | Q93: =IF(N93>Summary!$C$17,"Outlier","") | R93: =IF(L93="","None",L93) -> WINTER15
A94: ORD200092 | B94: 45453 | C94: C29568 | D94: Printer | E94: 4 | F94: 48.61 | G94: 203 Main St | H94: Online | I94: Shipped | J94: TRK46531075 | K94: 7 | L94: FREESHIP | M94: Facebook | N94: 194.44 | O94: =YEAR(B94) -> 2024 | P94: =DATE(YEAR(B94),MONTH(B94),1) -> 45444 | Q94: =IF(N94>Summary!$C$17,"Outlier","") | R94: =IF(L94="","None",L94) -> FREESHIP
A95: ORD200093 | B95: 44940 | C95: C97262 | D95: Desk | E95: 4 | F95: 431.01 | G95: 837 Main St | H95: Credit Card | I95: Returned | J95: TRK65990229 | K95: 7 | M95: Referral | N95: 1724.04 | O95: =YEAR(B95) -> 2023 | P95: =DATE(YEAR(B95),MONTH(B95),1) -> 44927 | Q95: =IF(N95>Summary!$C$17,"Outlier","") | R95: =IF(L95="","None",L95) -> None
A96: ORD200094 | B96: 44968 | C96: C79821 | D96: Chair | E96: 1 | F96: 531.18 | G96: 781 Main St | H96: Gift Card | I96: Returned | J96: TRK12780193 | K96: 6 | L96: WINTER15 | M96: Instagram | N96: 531.18 | O96: =YEAR(B96) -> 2023 | P96: =DATE(YEAR(B96),MONTH(B96),1) -> 44958 | Q96: =IF(N96>Summary!$C$17,"Outlier","") | R96: =IF(L96="","None",L96) -> WINTER15
A97: ORD200095 | B97: 45009 | C97: C76761 | D97: Printer | E97: 4 | F97: 117.51 | G97: 839 Main St | H97: Debit Card | I97: Returned | J97: TRK60179774 | K97: 7 | M97: Referral | N97: 470.04 | O97: =YEAR(B97) -> 2023 | P97: =DATE(YEAR(B97),MONTH(B97),1) -> 44986 | Q97: =IF(N97>Summary!$C$17,"Outlier","") | R97: =IF(L97="","None",L97) -> None
A98: ORD200096 | B98: 45444 | C98: C93007 | D98: Phone | E98: 2 | F98: 232.83 | G98: 103 Main St | H98: Gift Card | I98: Delivered | J98: TRK85696091 | K98: 7 | M98: Instagram | N98: 465.66 | O98: =YEAR(B98) -> 2024 | P98: =DATE(YEAR(B98),MONTH(B98),1) -> 45444 | Q98: =IF(N98>Summary!$C$17,"Outlier","") | R98: =IF(L98="","None",L98) -> None
A99: ORD200097 | B99: 45678 | C99: C15624 | D99: Tablet | E99: 5 | F99: 619.52 | G99: 922 Main St | H99: Debit Card | I99: Pending | J99: TRK40621141 | K99: 9 | M99: Email | N99: 3097.6 | O99: =YEAR(B99) -> 2025 | P99: =DATE(YEAR(B99),MONTH(B99),1) -> 45658 | Q99: =IF(N99>Summary!$C$17,"Outlier","") | R99: =IF(L99="","None",L99) -> None
A100: ORD200098 | B100: 44940 | C100: C70921 | D100: Printer | E100: 2 | F100: 228.54 | G100: 533 Main St | H100: Debit Card | I100: Pending | J100: TRK54983109 | K100: 3 | M100: Email | N100: 457.08 | O100: =YEAR(B100) -> 2023 | P100: =DATE(YEAR(B100),MONTH(B100),1) -> 44927 | Q100: =IF(N100>Summary!$C$17,"Outlier","") | R100: =IF(L100="","None",L100) -> None
...
